blink2png/__init__.py
blink2png/__main__.py
blink2png/core.py
blink2png-0.9.3.dist-info/LICENSE.md
blink2png-0.9.3.dist-info/METADATA
blink2png-0.9.3.dist-info/WHEEL
blink2png-0.9.3.dist-info/entry_points.txt
blink2png-0.9.3.dist-info/top_level.txt
blink2png-0.9.3.dist-info/zip-safe
blink2png-0.9.3.dist-info/RECORD
