Metadata-Version: 2.1
Name: blink2png
Version: 0.9.3
Summary: To take snapshot of web pages using Blink Engine and Qt5
Home-page: http://github.com/star-inc/blink2png
Author: Star Inc.
Author-email: "Star Inc." <star_inc@aol.com>
License: GNU General Public License
Platform: UNKNOWN
Classifier: Development Status :: 7 - Inactive
Classifier: Environment :: Web Environment
Classifier: Intended Audience :: Developers
Classifier: License :: OSI Approved :: GNU General Public License v3 or later (GPLv3+)
Classifier: Operating System :: MacOS :: MacOS X
Classifier: Operating System :: POSIX
Classifier: Programming Language :: Python :: 3.7
Classifier: Topic :: Software Development :: Bug Tracking
Classifier: Topic :: Multimedia :: Graphics :: Capture :: Screen Capture
Classifier: Topic :: Utilities
Requires-Dist: PyQt5
Requires-Dist: PyQtWebEngine
